{"errors":[],"warnings":[],"namedChunkGroups":{"polyfill":{"chunks":[2,0,7],"assets":["webpack-runtime-20b8c06f4f82d2dd45fb.js","webpack-runtime-20b8c06f4f82d2dd45fb.js.map","commons-7a5543d04495c6d4da65.js","commons-7a5543d04495c6d4da65.js.map","polyfill-5acc46d2c6294ee52fa0.js","polyfill-5acc46d2c6294ee52fa0.js.map"],"children":{},"childAssets":{}},"app":{"chunks":[2,6,0,3],"assets":["webpack-runtime-20b8c06f4f82d2dd45fb.js","webpack-runtime-20b8c06f4f82d2dd45fb.js.map","framework-d585a04b7d285a7760d6.js","framework-d585a04b7d285a7760d6.js.map","commons-7a5543d04495c6d4da65.js","commons-7a5543d04495c6d4da65.js.map","app-be110ea38896be006f1c.js","app-be110ea38896be006f1c.js.map"],"children":{},"childAssets":{}},"component---src-pages-404-js":{"chunks":[1,0,4],"assets":["styles.2bca5aae0967333c631a.css","styles-e9d24b1846c7d6eb9685.js","styles-e9d24b1846c7d6eb9685.js.map","commons-7a5543d04495c6d4da65.js","commons-7a5543d04495c6d4da65.js.map","component---src-pages-404-js-0db82d6eeee6490b835e.js","component---src-pages-404-js-0db82d6eeee6490b835e.js.map"],"children":{},"childAssets":{}},"component---src-pages-index-js":{"chunks":[1,0,5],"assets":["styles.2bca5aae0967333c631a.css","styles-e9d24b1846c7d6eb9685.js","styles-e9d24b1846c7d6eb9685.js.map","commons-7a5543d04495c6d4da65.js","commons-7a5543d04495c6d4da65.js.map","component---src-pages-index-js-47720a86964c49f0f1a0.js","component---src-pages-index-js-47720a86964c49f0f1a0.js.map"],"children":{},"childAssets":{}}},"assetsByChunkName":{"polyfill":["webpack-runtime-20b8c06f4f82d2dd45fb.js","commons-7a5543d04495c6d4da65.js","polyfill-5acc46d2c6294ee52fa0.js"],"app":["webpack-runtime-20b8c06f4f82d2dd45fb.js","framework-d585a04b7d285a7760d6.js","commons-7a5543d04495c6d4da65.js","app-be110ea38896be006f1c.js"],"component---src-pages-404-js":["styles.2bca5aae0967333c631a.css","styles-e9d24b1846c7d6eb9685.js","commons-7a5543d04495c6d4da65.js","component---src-pages-404-js-0db82d6eeee6490b835e.js"],"component---src-pages-index-js":["styles.2bca5aae0967333c631a.css","styles-e9d24b1846c7d6eb9685.js","commons-7a5543d04495c6d4da65.js","component---src-pages-index-js-47720a86964c49f0f1a0.js"]}}